pyvolutionary/__init__.py
pyvolutionary/abstract.py
pyvolutionary/african_vulture/__init__.py
pyvolutionary/african_vulture/african_vulture_optimization.py
pyvolutionary/african_vulture/models.py
pyvolutionary/ant_colony/__init__.py
pyvolutionary/ant_colony/ant_colony_optimization.py
pyvolutionary/ant_colony/models.py
pyvolutionary/ant_lion/__init__.py
pyvolutionary/ant_lion/ant_lion_optimization.py
pyvolutionary/ant_lion/models.py
pyvolutionary/aquila/__init__.py
pyvolutionary/aquila/aquila_optimization.py
pyvolutionary/aquila/models.py
pyvolutionary/archimede/__init__.py
pyvolutionary/archimede/archimede_optimization.py
pyvolutionary/archimede/models.py
pyvolutionary/bacterial_foraging/__init__.py
pyvolutionary/bacterial_foraging/bacterial_foraging_optimization.py
pyvolutionary/bacterial_foraging/models.py
pyvolutionary/bat/__init__.py
pyvolutionary/bat/bat_optimization.py
pyvolutionary/bat/models.py
pyvolutionary/battle_royale/__init__.py
pyvolutionary/battle_royale/battle_royale_optimization.py
pyvolutionary/battle_royale/models.py
pyvolutionary/bee_colony/__init__.py
pyvolutionary/bee_colony/bee_colony_optimization.py
pyvolutionary/bee_colony/models.py
pyvolutionary/biogeography_based/__init__.py
pyvolutionary/biogeography_based/biogeography_based_optimization.py
pyvolutionary/biogeography_based/models.py
pyvolutionary/brain_storm/__init__.py
pyvolutionary/brain_storm/brain_storm_optimization.py
pyvolutionary/brain_storm/improved_brain_storm_optimization.py
pyvolutionary/brain_storm/models.py
pyvolutionary/brown_bear/__init__.py
pyvolutionary/brown_bear/brown_bear_optimization.py
pyvolutionary/brown_bear/models.py
pyvolutionary/camel_caravan/__init__.py
pyvolutionary/camel_caravan/camel_caravan_optimization.py
pyvolutionary/camel_caravan/models.py
pyvolutionary/cat_swarm/__init__.py
pyvolutionary/cat_swarm/cat_swarm_optimization.py
pyvolutionary/cat_swarm/models.py
pyvolutionary/chaos_game/__init__.py
pyvolutionary/chaos_game/chaos_game_optimization.py
pyvolutionary-2.6.5.dist-info/LICENSE
pyvolutionary-2.6.5.dist-info/METADATA
pyvolutionary-2.6.5.dist-info/WHEEL
pyvolutionary-2.6.5.dist-info/RECORD
