Metadata-Version: 2.3
Name: pyVolutionary
Version: 2.6.5
Summary: pyVolutionary is a package collecting metaheuristic algorithms, available for free usage and able to solve a wide range of optimization problems.
License: MIT
Author: Matteo Cacciola
Author-email: matteo.cacciola@gmail.com
Requires-Python: >=3.10
Classifier: Development Status :: 5 - Production/Stable
Classifier: License :: OSI Approved :: MIT License
Classifier: Programming Language :: Python :: 3
Classifier: Programming Language :: Python :: 3.10
Classifier: Programming Language :: Python :: 3.11
Classifier: Programming Language :: Python :: 3.12
Classifier: Programming Language :: Python :: 3.13
Classifier: Topic :: Scientific/Engineering
Classifier: Topic :: Software Development
Requires-Dist: numpy (>=2.1.1,<3.0.0)
Requires-Dist: pandas (>=2.2.0,<3.0.0)
Requires-Dist: pydantic (>=2.9.0,<3.0.0)
Requires-Dist: scipy (>=1.12.0,<2.0.0)
Project-URL: Repository, https://github.com/matteocacciola/pyvolutionary
